ConvertColour/Colour.py
ConvertColour/HexColour.py
ConvertColour/RGBColour.py
ConvertColour/RYBColour.py
ConvertColour/__init__.py
ConvertColour/converters/__init__.py
ConvertColour/converters/hex_to_rgb.py
ConvertColour/converters/rgb_to_hex.py
ConvertColour/converters/rgb_to_ryb.py
ConvertColour/converters/ryb_to_rgb.py
convertcolour-0.0.1.dist-info/METADATA
convertcolour-0.0.1.dist-info/WHEEL
convertcolour-0.0.1.dist-info/licenses/LICENSE
convertcolour-0.0.1.dist-info/RECORD
