Metadata-Version: 2.1
Name: ConvertColour
Version: 0.0.1
Summary: A simple Python colour converter!
Project-URL: Documentation, http://convertcolour.rtfd.io/
Project-URL: Homepage, https://github.com/Pigeon43/ConvertColour
Project-URL: Issues/Bugs, https://github.com/Pigeon43/ConvertColour/issues
Project-URL: PyPI, https://pypi.org/project/convertcolour/
Author-email: Pigeon43 <rapidpigeon43@gmail.com>
License-File: LICENSE
Classifier: License :: OSI Approved :: MIT License
Classifier: Operating System :: OS Independent
Classifier: Programming Language :: Python :: 3
